festung/__init__.py
festung/_private.py
festung/dbapi.py
festung/exceptions.py
festung/pool.py
festung/types.py
festung-0.11.1.dist-info/AUTHORS
festung-0.11.1.dist-info/LICENSE
festung-0.11.1.dist-info/METADATA
festung-0.11.1.dist-info/WHEEL
festung-0.11.1.dist-info/pbr.json
festung-0.11.1.dist-info/top_level.txt
festung-0.11.1.dist-info/RECORD
