Metadata-Version: 2.1
Name: festung
Version: 0.11.1
Summary: DBAPIv2 to Festung
Home-page: https://github.com/figome/python-festung
Author: figo GmbH
Author-email: develop@figo.io
License: ISC
Keywords: festung
Requires-Dist: certifi (==2018.10.15)
Requires-Dist: chardet (==3.0.4)
Requires-Dist: enum34 (==1.1.6)
Requires-Dist: furl (==2.0.0)
Requires-Dist: idna (==2.7)
Requires-Dist: orderedmultidict (==1.0)
Requires-Dist: requests (==2.20.0)
Requires-Dist: simplejson (==3.16.0)
Requires-Dist: six (==1.11.0)
Requires-Dist: urllib3 (==1.24)
